mainproject/stationSystem/7SegmentDisplay/7SegDisplay.v
/*-------------------------------------------------------------
    Project Lab 1 - Main Project
       Program by: Zachary Bonneau
    Creation Date: 10/20/2023
     Program Name: 7SegDisplay.v
    SubProgram of: Station System
  
    Program Description:
        7 Segment Display configures the anodes and cathodes of the 
        Basys3 board 7 Segment Display.

    Inputs:
        DisplayCLK - 381 Hz clock for multiplexing
        decimalTemp - 8-bit BCD value of temperature
        display - enables/disables entire display module
    
    Outputs:
        A [3:0] - 4 anodes for 4 digits of 7-seg display
        seg [7:0] - 8 bit configuration for 7 segments + decimal point (dp)      

    Internal Signals:
        ASEL [1:0] - Anode select register, chooses between A0 - A3

*///-----------------------------------------------------------

module SSEG_Display(
    input displayCLK, display,
    input [7:0] decimalTemp,
    output [3:0] A,
    output reg [7:0] sseg = 8'hFF
    );

    //----------------------------
    // ASEL code block

    reg [1:0] ASEL = 0; 

    always@(posedge displayCLK) begin
        ASEL = ASEL + 1;
    end

    //----------------------------
    // digit 3-0 code block
    // digits 3, 2 use digitDriver modules

    wire [7:0] SSEG3, SSEG2;

    digitDriver Digit3(decimalTemp[7:4], SSEG3);
    digitDriver Digit2(decimalTemp[3:0], SSEG2);

    reg [7:0] SSEG1 = 8'b11111111; // blank code
    reg [7:0] SSEG0 = 8'b01100011; // "C"

    //----------------------------
    // digit Multiplexer

    always@(ASEL) begin 
        // Multiplexer selects between digit configurations
        case (ASEL)
            0: sseg <= SSEG0;
            1: sseg <= SSEG1;
            2: sseg <= SSEG2;
            3: sseg <= SSEG3;
        endcase
    end

    //----------------------------
    // Anode Selection Assignments

    assign A[3] = ~(display &  ASEL[1] &  ASEL[0]);
    assign A[2] = ~(display &  ASEL[1] & ~ASEL[0]);
    assign A[1] = ~(display & ~ASEL[1] &  ASEL[0]);
    assign A[0] = ~(display & ~ASEL[1] & ~ASEL[0]);

endmodule

//-------------------------------
/*
    Digit Driver: converts 4-bit BCD to 7seg configurations
        - used for digit 3/2
*/

module digitDriver(
    input [3:0] num,
    output reg [7:0] SSEG
);
    always@(num) begin
        case (num)
                // abcdefg-dp
            0:  SSEG <= 8'b00000011;
            1:  SSEG <= 8'b10011111;
            2:  SSEG <= 8'b00100101;
            3:  SSEG <= 8'b00001101;
            4:  SSEG <= 8'b10011001;
            5:  SSEG <= 8'b01001001;
            6:  SSEG <= 8'b01000001;
            7:  SSEG <= 8'b01110011;
            8:  SSEG <= 8'b00000001;
            9:  SSEG <= 8'b00001001;
            10: SSEG <= 8'b01111110; // 10-14: error codes - num should be 0-9, 15 for blank
            11: SSEG <= 8'b10111110;
            12: SSEG <= 8'b11011110;
            13: SSEG <= 8'b11101110;
            14: SSEG <= 8'b11110110;
            15: SSEG <= 8'b11111111; // blank code
        endcase
    end
endmodule

mainproject/stationSystem/7SegmentDisplay/7SegDriverTestbench.v
/*-------------------------------------------------------------
    Project Lab 1 - Main Project
       Program by: Zachary Bonneau
    Creation Date: 10/20/2023
     Program Name: 7SegDriverTestbench.v
    SubProgram of: Station System
  
    Program Description:
        Runs a simulated testbench of 7 Segment Display

*///-----------------------------------------------------------

// directive calls
`include "mainproject\stationSystem\7SegmentDisplay\7SegDisplay.v"

module testbench();
    reg displayCLK = 0;
    reg display = 0;
    reg [7:0] decimalTemp = 8'h01;
    wire [3:0] A;
    wire [7:0] sseg;

    SSEG_Display UUT(displayCLK, display,
                     decimalTemp, A, sseg);
    
    always begin
        #1; displayCLK = ~displayCLK;
    end

    initial begin
        $dumpfile("7SegDisplay.vcd");
        $dumpvars(0, testbench);
        #8; display = 1;
        #8; decimalTemp = 8'h23;
        #8; decimalTemp = 8'h45;
        #8; decimalTemp = 8'h67;
        #8; decimalTemp = 8'h89;
        #8; decimalTemp = 8'hAB;
        #8; decimalTemp = 8'hCD;
        #8; decimalTemp = 8'hEF;
        #8; display = 0;
        #8;
        $finish;
    end
endmodule

mainproject/Waveforms/7SegDisplay.vcd
$date
	Fri Oct 20 11:29:50 2023
$end
$version
	Icarus Verilog
$end
$timescale
	1s
$end
$scope module testbench $end
$var wire 8 ! sseg [7:0] $end
$var wire 4 " A [3:0] $end
$var reg 8 # decimalTemp [7:0] $end
$var reg 1 $ display $end
$var reg 1 % displayCLK $end
$scope module UUT $end
$var wire 8 & decimalTemp [7:0] $end
$var wire 1 $ display $end
$var wire 1 % displayCLK $end
$var wire 8 ' SSEG3 [7:0] $end
$var wire 8 ( SSEG2 [7:0] $end
$var wire 4 ) A [3:0] $end
$var reg 2 * ASEL [1:0] $end
$var reg 8 + SSEG0 [7:0] $end
$var reg 8 , SSEG1 [7:0] $end
$var reg 8 - sseg [7:0] $end
$scope module Digit2 $end
$var wire 4 . num [3:0] $end
$var reg 8 / SSEG [7:0] $end
$upscope $end
$scope module Digit3 $end
$var wire 4 0 num [3:0] $end
$var reg 8 1 SSEG [7:0] $end
$upscope $end
$upscope $end
$upscope $end
$enddefinitions $end
$comment Show the parameter values. $end
$dumpall
$end
#0
$dumpvars
b11 1
b0 0
b10011111 /
b1 .
b1100011 -
b11111111 ,
b1100011 +
b0 *
b1111 )
b10011111 (
b11 '
b1 &
0%
0$
b1 #
b1111 "
b1100011 !
$end
#1
b11111111 !
b11111111 -
b1 *
1%
#2
0%
#3
b10011111 !
b10011111 -
b10 *
1%
#4
0%
#5
b11 !
b11 -
b11 *
1%
#6
0%
#7
b1100011 !
b1100011 -
b0 *
1%
#8
b1110 "
b1110 )
0%
1$
#9
b11111111 !
b11111111 -
b1101 "
b1101 )
b1 *
1%
#10
0%
#11
b10011111 !
b10011111 -
b1011 "
b1011 )
b10 *
1%
#12
0%
#13
b11 !
b11 -
b111 "
b111 )
b11 *
1%
#14
0%
#15
b1100011 !
b1100011 -
b1110 "
b1110 )
b0 *
1%
#16
b100101 '
b100101 1
b1101 (
b1101 /
b10 0
b11 .
0%
b100011 #
b100011 &
#17
b11111111 !
b11111111 -
b1101 "
b1101 )
b1 *
1%
#18
0%
#19
b1101 !
b1101 -
b1011 "
b1011 )
b10 *
1%
#20
0%
#21
b100101 !
b100101 -
b111 "
b111 )
b11 *
1%
#22
0%
#23
b1100011 !
b1100011 -
b1110 "
b1110 )
b0 *
1%
#24
b10011001 '
b10011001 1
b1001001 (
b1001001 /
b100 0
b101 .
0%
b1000101 #
b1000101 &
#25
b11111111 !
b11111111 -
b1101 "
b1101 )
b1 *
1%
#26
0%
#27
b1001001 !
b1001001 -
b1011 "
b1011 )
b10 *
1%
#28
0%
#29
b10011001 !
b10011001 -
b111 "
b111 )
b11 *
1%
#30
0%
#31
b1100011 !
b1100011 -
b1110 "
b1110 )
b0 *
1%
#32
b1000001 '
b1000001 1
b1110011 (
b1110011 /
b110 0
b111 .
0%
b1100111 #
b1100111 &
#33
b11111111 !
b11111111 -
b1101 "
b1101 )
b1 *
1%
#34
0%
#35
b1110011 !
b1110011 -
b1011 "
b1011 )
b10 *
1%
#36
0%
#37
b1000001 !
b1000001 -
b111 "
b111 )
b11 *
1%
#38
0%
#39
b1100011 !
b1100011 -
b1110 "
b1110 )
b0 *
1%
#40
b1 '
b1 1
b1001 (
b1001 /
b1000 0
b1001 .
0%
b10001001 #
b10001001 &
#41
b11111111 !
b11111111 -
b1101 "
b1101 )
b1 *
1%
#42
0%
#43
b1001 !
b1001 -
b1011 "
b1011 )
b10 *
1%
#44
0%
#45
b1 !
b1 -
b111 "
b111 )
b11 *
1%
#46
0%
#47
b1100011 !
b1100011 -
b1110 "
b1110 )
b0 *
1%
#48
b1111110 '
b1111110 1
b10111110 (
b10111110 /
b1010 0
b1011 .
0%
b10101011 #
b10101011 &
#49
b11111111 !
b11111111 -
b1101 "
b1101 )
b1 *
1%
#50
0%
#51
b10111110 !
b10111110 -
b1011 "
b1011 )
b10 *
1%
#52
0%
#53
b1111110 !
b1111110 -
b111 "
b111 )
b11 *
1%
#54
0%
#55
b1100011 !
b1100011 -
b1110 "
b1110 )
b0 *
1%
#56
b11011110 '
b11011110 1
b11101110 (
b11101110 /
b1100 0
b1101 .
0%
b11001101 #
b11001101 &
#57
b11111111 !
b11111111 -
b1101 "
b1101 )
b1 *
1%
#58
0%
#59
b11101110 !
b11101110 -
b1011 "
b1011 )
b10 *
1%
#60
0%
#61
b11011110 !
b11011110 -
b111 "
b111 )
b11 *
1%
#62
0%
#63
b1100011 !
b1100011 -
b1110 "
b1110 )
b0 *
1%
#64
b11110110 '
b11110110 1
b11111111 (
b11111111 /
b1110 0
b1111 .
0%
b11101111 #
b11101111 &
#65
b11111111 !
b11111111 -
b1101 "
b1101 )
b1 *
1%
#66
0%
#67
b1011 "
b1011 )
b10 *
1%
#68
0%
#69
b11110110 !
b11110110 -
b111 "
b111 )
b11 *
1%
#70
0%
#71
b1100011 !
b1100011 -
b1110 "
b1110 )
b0 *
1%
#72
b1111 "
b1111 )
0%
0$
#73
b11111111 !
b11111111 -
b1 *
1%
#74
0%
#75
b10 *
1%
#76
0%
#77
b11110110 !
b11110110 -
b11 *
1%
#78
0%
#79
b1100011 !
b1100011 -
b0 *
1%
