mainproject/driveSystem/movementSystem/movement.v
/*-------------------------------------------------------------
    Project Lab 1 - Main Project
       Program by: Zachary Bonneau
    Creation Date: 10/12/2023
     Program Name: movement.v
    SubProgram of: movement system
  
    Program Description:
        This program constructs the movement system state machine. This machine
        evaluates the condition of 3 IPS sensors (L, C*, R) and determines the type 
        of track it is following. It uses this information to determine how to drive 
        motors A/B of the rover.

        L   C*  R   |   Track Type
        ------------|-------------
        0   0   0   |   Straight (ST)
        0   0   1   |   Curve Right (CR)
        0   1   0   |   NONE
        0   1   1   |   Right 90 deg (R90)
        1   0   0   |   Curve Left (CL)
        1   0   1   |   Crossroad (Cross)
        1   1   0   |   Left 90 deg (L90)
        1   1   1   |   Crossroad (no center line detected, but no T-Junctions exist on track)

        Note: C* bc C is an inverted input (active low)

    Inputs:
        CLK     - timing clock
        L,C,R   - IPS sensors (determine track position/angle relative to rover)
    
    Outputs:
        [1:0] DriveA/B - drive strength sent to PWM generator for motors A/B

    Internal Signals:
        [3:0] state - state machine register
        CrossNum    - tracks crossroads events

*///-----------------------------------------------------------

module movement(
    input CLK, L, C, R,
    output reg [1:0] DriveA = 0, 
    output reg [1:0] DriveB = 0
);
    // local params to represent track types
    localparam track_ST     = 3'b000;
    localparam track_CR     = 3'b001;
    localparam track_None   = 3'b010;
    localparam track_R90    = 3'b011;
    localparam track_LC     = 3'b100;
    localparam track_Cross  = 3'b101;
    localparam track_L90    = 3'b110;
    localparam track_CrossT = 3'b111;

    // local params to represent different state values
    localparam OFF      = 4'b0000;
    localparam ST       = 4'b0001;
    localparam CL       = 4'b0010;
    localparam L90      = 4'b0011;
    localparam CR       = 4'b0100;
    localparam R90      = 4'b0101;
    localparam Cross    = 4'b0110;
    localparam CST      = 4'b1001;
    localparam C90      = 4'b1101;

    reg [3:0] state = OFF;
    reg CrossNum = 0; // 0: first time crossing, 1: second time crossing

    // inside this block is a set of nested case statements which compute:
        // The next state to go to
        // how to configure output registers

        // example case iteration:
            // state: 
                // set DriveA/DriveB
                // nested case (IPS sensors)
                    // set next state according to State machine
                // end nested case
            // end state
    always@(posedge CLK) begin
        case (state)
            OFF: begin
                DriveA <= 0;
                DriveB <= 0;
                casex({L,C,R})
                    track_ST:   state <= ST;
                    track_None: state <= OFF;
                    3'b0X1:     state <= CR;
                    3'b1X0:     state <= CL;
                    3'b1X1:     state <= CR;
                endcase
            end

            ST: begin
                DriveA <= 1;
                DriveB <= 1;
                casex({L,C,R})
                    3'b0X0: state <= ST;
                    3'b1X0: state <= CL;
                    3'b0X1: state <= CR;
                    3'b1X1: state <= Cross;
                endcase
            end

            CL: begin
                DriveA <= 1;
                DriveB <= 2;
                casex({L,C,R})
                    3'b00X: state <= ST;
                    3'b1X1: state <= Cross;
                    track_R90:  state <= Cross;
                    track_LC:   state <= CL;
                    track_None: state <= CL;
                    track_L90:  state <= L90;
                endcase
            end

            L90: begin
                DriveA <= 0;
                DriveB <= 2;
                casex({L,C,R})
                    3'bX0X: state <= CL;
                    3'bX1X: state <= L90;
                endcase
            end

            CR: begin
                DriveA <= 2;
                DriveB <= 1;
                casex({L,C,R})
                    3'bX00:     state <= ST;
                    3'b1X1:     state <= Cross;
                    track_L90:  state <= Cross;
                    track_CR:   state <= CR;
                    track_None: state <= CR;
                    track_R90:  state <= R90;
                endcase
            end

            R90: begin
                DriveA <= 2;
                DriveB <= 0;
                casex({L,C,R})
                    3'bX1X: state <= R90;
                    3'bX0X: state <= CR;
                endcase
            end

            Cross: begin
                case (CrossNum)
                    0: begin
                        state = C90;
                        CrossNum = 1;
                    end

                    1: begin
                        state = CST;
                        CrossNum = 0;
                    end
                endcase
            end

            CST: begin
                DriveA <= 1;
                DriveB <= 1;
                case({L,C,R})
                    track_ST:   state <= ST;
                    default:    state <= CST;
                endcase
            end

            C90: begin
                DriveA <= 2;
                DriveB <= 0;
                casex({L,C,R})
                    3'bX0X: state <= C90;
                    3'bX1X: state <= R90;
                endcase
            end

            default: begin
                state  <= OFF;
                DriveA <= 0;
                DriveB <= 0;
            end
        endcase
    end
endmodule

mainproject/driveSystem/movementSystem/moveTestbench.v
/*-------------------------------------------------------------
    Project Lab 1 - Main Project
       Program by: Zachary Bonneau
    Creation Date: 10/12/2023
     Program Name: moveTestbench.v
    SubProgram of: Movement system
  
    Program Description:
        This program runs a simulated testbench of the 
        massive movement system state machine.     

        Note: Reference move.vcd for visual depiction. The State machine updates on the
            positive edge of ACLK, as well as the driveA/B registers. These registers update
            to the OLD STATE. That is, DriveA and DriveB always update 1 CLK cycle (1 mS) after the state 

*///-----------------------------------------------------------
`include "mainproject\driveSystem\movementSystem\movement.v"
`timescale 100us/100us

module testbench;
    reg ACLK = 0;
    reg [2:0] IPS; // 3 bits: L, C, R
    wire [1:0] DriveA, DriveB; // sent to motor PWM generator

    movement UUT(ACLK, IPS[2], IPS[1], IPS[0], DriveA, DriveB);

    always begin
        #5; ACLK = ~ACLK; // clk period = 2 x (5 x 100 uS) = 1 mS
    end

    initial begin
        $dumpfile("move.vcd");
        $dumpvars(0,testbench);
        IPS = 0; #100;      // OFF   -> Straight     (ST)
        IPS = 3'b100; #50;  // ST    -> Curve Left   (CL)
        IPS = 3'b000; #50;  // CL    -> ST
        IPS = 3'b001; #50;  // ST    -> Curve Right  (CR)
        IPS = 3'b011; #50;  // CR    -> Right 90 deg (R90)
        IPS = 3'b000; #50;  // R90   -> CR   -> ST
        IPS = 3'b101; #50;  // ST    -> Crossover    (Cross)
        IPS = 3'b111; #50;  // Cross -> Cross 90     (C90 - Cross Register <= 1)
        IPS = 3'b000; #50;  // C90   -> R90  -> CR   -> ST
        IPS = 3'b110; #50;  // ST    -> CL   -> Left 90 (L90)
        IPS = 3'b101; #50;  // L90   -> Cl   -> Cross   -> Cross Straight (CST - Cross Register <= 0)
        IPS = 3'b000; #50;  // CST   -> ST
        $finish;
    end
endmodule

mainproject/Waveforms/move.vcd
$date
	Thu Oct 12 23:30:44 2023
$end
$version
	Icarus Verilog
$end
$timescale
	100us
$end
$scope module testbench $end
$var wire 2 ! DriveB [1:0] $end
$var wire 2 " DriveA [1:0] $end
$var reg 1 # ACLK $end
$var reg 3 $ IPS [2:0] $end
$scope module UUT $end
$var wire 1 % C $end
$var wire 1 # CLK $end
$var wire 1 & L $end
$var wire 1 ' R $end
$var parameter 4 ( C90 $end
$var parameter 4 ) CL $end
$var parameter 4 * CR $end
$var parameter 4 + CST $end
$var parameter 4 , Cross $end
$var parameter 4 - L90 $end
$var parameter 4 . OFF $end
$var parameter 4 / R90 $end
$var parameter 4 0 ST $end
$var parameter 3 1 track_CR $end
$var parameter 3 2 track_Cross $end
$var parameter 3 3 track_CrossT $end
$var parameter 3 4 track_L90 $end
$var parameter 3 5 track_LC $end
$var parameter 3 6 track_None $end
$var parameter 3 7 track_R90 $end
$var parameter 3 8 track_ST $end
$var reg 1 9 CrossNum $end
$var reg 2 : DriveA [1:0] $end
$var reg 2 ; DriveB [1:0] $end
$var reg 4 < state [3:0] $end
$upscope $end
$upscope $end
$enddefinitions $end
$comment Show the parameter values. $end
$dumpall
b0 8
b11 7
b10 6
b100 5
b110 4
b111 3
b101 2
b1 1
b1 0
b101 /
b0 .
b11 -
b110 ,
b1001 +
b100 *
b10 )
b1101 (
$end
#0
$dumpvars
b0 <
b0 ;
b0 :
09
0'
0&
0%
b0 $
0#
b0 "
b0 !
$end
#5
b1 <
1#
#10
0#
#15
b1 !
b1 ;
b1 "
b1 :
1#
#20
0#
#25
1#
#30
0#
#35
1#
#40
0#
#45
1#
#50
0#
#55
1#
#60
0#
#65
1#
#70
0#
#75
1#
#80
0#
#85
1#
#90
0#
#95
1#
#100
1&
0#
b100 $
#105
b10 <
1#
#110
0#
#115
b10 !
b10 ;
1#
#120
0#
#125
1#
#130
0#
#135
1#
#140
0#
#145
1#
#150
0&
0#
b0 $
#155
b1 <
1#
#160
0#
#165
b1 !
b1 ;
1#
#170
0#
#175
1#
#180
0#
#185
1#
#190
0#
#195
1#
#200
1'
0#
b1 $
#205
b100 <
1#
#210
0#
#215
b10 "
b10 :
1#
#220
0#
#225
1#
#230
0#
#235
1#
#240
0#
#245
1#
#250
1%
0#
b11 $
#255
b101 <
1#
#260
0#
#265
b0 !
b0 ;
1#
#270
0#
#275
1#
#280
0#
#285
1#
#290
0#
#295
1#
#300
0%
0'
0#
b0 $
#305
b100 <
1#
#310
0#
#315
b1 <
b1 !
b1 ;
1#
#320
0#
#325
b1 "
b1 :
1#
#330
0#
#335
1#
#340
0#
#345
1#
#350
1&
1'
0#
b101 $
#355
b110 <
1#
#360
0#
#365
19
b1101 <
1#
#370
0#
#375
b0 !
b0 ;
b10 "
b10 :
1#
#380
0#
#385
1#
#390
0#
#395
1#
#400
1%
0#
b111 $
#405
b101 <
1#
#410
0#
#415
1#
#420
0#
#425
1#
#430
0#
#435
1#
#440
0#
#445
1#
#450
0&
0%
0'
0#
b0 $
#455
b100 <
1#
#460
0#
#465
b1 <
b1 !
b1 ;
1#
#470
0#
#475
b1 "
b1 :
1#
#480
0#
#485
1#
#490
0#
#495
1#
#500
1&
1%
0#
b110 $
#505
b10 <
1#
#510
0#
#515
b11 <
b10 !
b10 ;
1#
#520
0#
#525
b0 "
b0 :
1#
#530
0#
#535
1#
#540
0#
#545
1#
#550
0%
1'
0#
b101 $
#555
b10 <
1#
#560
0#
#565
b110 <
b1 "
b1 :
1#
#570
0#
#575
09
b1001 <
1#
#580
0#
#585
b1 !
b1 ;
1#
#590
0#
#595
1#
#600
0&
0'
0#
b0 $
#605
b1 <
1#
