miniproject/T-FF.v
/*-------------------------------------------------------------
    Project Lab 1 - Mini Motor Project
       Program by: Zachary Bonneau
    Creation Date: 09/06/2023
     Program Name: T-FF_negCLK.v
    SubProgram of: Mini Motor
  
    Program Description:
    The T-FF is a standard data register that inverts every clock cyle. 
    This program has two modules: TFF_POS and TFF_NEG
     - POS flips on rising edge of CLK
     - NEG flips on negative edge of CLK

    Inputs:
        CLK - Clock src
    
    Outputs:
        T - non-inverted data value
*/


module TFF_POS(T, CLK);
    // positive edge TFF
    input CLK;
    output reg T = 0;

    always@(posedge CLK) begin
        // flip T on rising edge
        T = ~T;
    end
endmodule

module TFF_NEG(T, CLK);
    // negative edge TFF
    input CLK;
    output reg T = 0;

    always@(negedge CLK) begin
        // flip T on falling edge
        T = ~T;
    end
endmodule

/*
module testbench;
    // testbench module - tests posedge and negedge signals
    reg CLK = 0;
    wire T_POS, T_NEG;

    always begin
       #1; CLK = ~CLK;
    end

        TFF_POS UUT1(T_POS, CLK);
    TFF_NEG UUT2(T_NEG, CLK);

    initial begin
        $dumpfile("TFF_waveform.vcd");
        $dumpvars(0, testbench);
        #10;                            // no control necessary, just wait 10
        $finish;
    end
endmodule

*/

miniproject/PWM_SYS/TCR.v
/*-------------------------------------------------------------
    Project Lab 1 - Mini Motor Project
       Program by: Zachary Bonneau
    Creation Date: 09/06/2023
     Program Name: TCR.v
    SubProgram of: PWM System

    includes:
        T-FF.v
  
    Program Description:
    The Timer/Counter does the following:
        - sets the period of the PWM signal
        - sends the 7-bit value TCR to the output block
        - sends the enable signal E to the CCR and output blocks

    Inputs:
        CLK - system clock source
    
    Outputs:
        TCR [6:0] - 7-bit data output sent to PWM_OUT block
        E         - control output sent to CCR and PWM_OUT
*/

`include "\miniproject\T-FF.v"

module TCBlock(TCR, E, CLK);
    input CLK;

    output E;
    wire [6:0] T;
    output [6:0] TCR;

    TFF_NEG T0(TCR[0], CLK);
    TFF_NEG T1(TCR[1], TCR[0]);
    TFF_NEG T2(TCR[2], TCR[1]);
    TFF_NEG T3(TCR[3], TCR[2]);
    TFF_NEG T4(TCR[4], TCR[3]);
    TFF_NEG T5(TCR[5], TCR[4]);
    TFF_NEG T6(TCR[6], TCR[5]);

    assign E = ~(TCR[0] | TCR[1] | TCR[2] 
      | TCR[3] | TCR[4] | TCR[5] | TCR[6]);
    
endmodule

module testbench;
    // Testbench - Configure and Test TCR to 
    //   evaluate chained T-FFs and E signal
    reg CLK = 1;
    wire E;
    wire [6:0] TCR;

    TCBlock UUT(TCR, E, CLK);

    always begin
        #1; CLK = ~CLK;
    end

    initial begin
        $dumpfile("TCR_waveform.vcd");
        $dumpvars(0, testbench);
        #256;
        $finish;
    end
endmodule

build/TCR_waveform.vcd
$date
	Mon Sep 11 20:30:11 2023
$end
$version
	Icarus Verilog
$end
$timescale
	1s
$end
$scope module testbench $end
$var wire 7 ! TCR [6:0] $end
$var wire 1 " E $end
$var reg 1 # CLK $end
$scope module UUT $end
$var wire 1 # CLK $end
$var wire 1 " E $end
$var wire 7 $ TCR [6:0] $end
$scope module T0 $end
$var wire 1 # CLK $end
$var reg 1 % T $end
$upscope $end
$scope module T1 $end
$var wire 1 & CLK $end
$var reg 1 ' T $end
$upscope $end
$scope module T2 $end
$var wire 1 ( CLK $end
$var reg 1 ) T $end
$upscope $end
$scope module T3 $end
$var wire 1 * CLK $end
$var reg 1 + T $end
$upscope $end
$scope module T4 $end
$var wire 1 , CLK $end
$var reg 1 - T $end
$upscope $end
$scope module T5 $end
$var wire 1 . CLK $end
$var reg 1 / T $end
$upscope $end
$scope module T6 $end
$var wire 1 0 CLK $end
$var reg 1 1 T $end
$upscope $end
$upscope $end
$upscope $end
$enddefinitions $end
$comment Show the parameter values. $end
$dumpall
$end
#0
$dumpvars
11
10
1/
1.
1-
1,
1+
1*
1)
1(
1'
0&
0%
b1111110 $
1#
0"
b1111110 !
$end
#1
1&
b1111111 !
b1111111 $
1%
0#
#2
1#
#3
1"
01
00
0/
0.
0-
0,
0+
0*
0)
0(
0'
0&
b0 !
b0 $
0%
0#
#4
1#
#5
0"
1&
b1 !
b1 $
1%
0#
#6
1#
#7
0"
1(
1'
0&
b10 !
b10 $
0%
0#
#8
1#
#9
1&
b11 !
b11 $
1%
0#
#10
1#
#11
1*
1)
0(
0'
0&
b100 !
b100 $
0%
0#
#12
1#
#13
1&
b101 !
b101 $
1%
0#
#14
1#
#15
1(
1'
0&
b110 !
b110 $
0%
0#
#16
1#
#17
1&
b111 !
b111 $
1%
0#
#18
1#
#19
0"
1,
1+
0*
0)
0(
0'
0&
b1000 !
b1000 $
0%
0#
#20
1#
#21
1&
b1001 !
b1001 $
1%
0#
#22
1#
#23
1(
1'
0&
b1010 !
b1010 $
0%
0#
#24
1#
#25
1&
b1011 !
b1011 $
1%
0#
#26
1#
#27
1*
1)
0(
0'
0&
b1100 !
b1100 $
0%
0#
#28
1#
#29
1&
b1101 !
b1101 $
1%
0#
#30
1#
#31
1(
1'
0&
b1110 !
b1110 $
0%
0#
#32
1#
#33
1&
b1111 !
b1111 $
1%
0#
#34
1#
#35
1.
1-
0,
0+
0*
0)
0(
0'
0&
b10000 !
b10000 $
0%
0#
#36
1#
#37
1&
b10001 !
b10001 $
1%
0#
#38
1#
#39
1(
1'
0&
b10010 !
b10010 $
0%
0#
#40
1#
#41
1&
b10011 !
b10011 $
1%
0#
#42
1#
#43
1*
1)
0(
0'
0&
b10100 !
b10100 $
0%
0#
#44
1#
#45
1&
b10101 !
b10101 $
1%
0#
#46
1#
#47
1(
1'
0&
b10110 !
b10110 $
0%
0#
#48
1#
#49
1&
b10111 !
b10111 $
1%
0#
#50
1#
#51
1,
1+
0*
0)
0(
0'
0&
b11000 !
b11000 $
0%
0#
#52
1#
#53
1&
b11001 !
b11001 $
1%
0#
#54
1#
#55
1(
1'
0&
b11010 !
b11010 $
0%
0#
#56
1#
#57
1&
b11011 !
b11011 $
1%
0#
#58
1#
#59
1*
1)
0(
0'
0&
b11100 !
b11100 $
0%
0#
#60
1#
#61
1&
b11101 !
b11101 $
1%
0#
#62
1#
#63
1(
1'
0&
b11110 !
b11110 $
0%
0#
#64
1#
#65
1&
b11111 !
b11111 $
1%
0#
#66
1#
#67
0"
10
1/
0.
0-
0,
0+
0*
0)
0(
0'
0&
b100000 !
b100000 $
0%
0#
#68
1#
#69
1&
b100001 !
b100001 $
1%
0#
#70
1#
#71
1(
1'
0&
b100010 !
b100010 $
0%
0#
#72
1#
#73
1&
b100011 !
b100011 $
1%
0#
#74
1#
#75
1*
1)
0(
0'
0&
b100100 !
b100100 $
0%
0#
#76
1#
#77
1&
b100101 !
b100101 $
1%
0#
#78
1#
#79
1(
1'
0&
b100110 !
b100110 $
0%
0#
#80
1#
#81
1&
b100111 !
b100111 $
1%
0#
#82
1#
#83
1,
1+
0*
0)
0(
0'
0&
b101000 !
b101000 $
0%
0#
#84
1#
#85
1&
b101001 !
b101001 $
1%
0#
#86
1#
#87
1(
1'
0&
b101010 !
b101010 $
0%
0#
#88
1#
#89
1&
b101011 !
b101011 $
1%
0#
#90
1#
#91
1*
1)
0(
0'
0&
b101100 !
b101100 $
0%
0#
#92
1#
#93
1&
b101101 !
b101101 $
1%
0#
#94
1#
#95
1(
1'
0&
b101110 !
b101110 $
0%
0#
#96
1#
#97
1&
b101111 !
b101111 $
1%
0#
#98
1#
#99
1.
1-
0,
0+
0*
0)
0(
0'
0&
b110000 !
b110000 $
0%
0#
#100
1#
#101
1&
b110001 !
b110001 $
1%
0#
#102
1#
#103
1(
1'
0&
b110010 !
b110010 $
0%
0#
#104
1#
#105
1&
b110011 !
b110011 $
1%
0#
#106
1#
#107
1*
1)
0(
0'
0&
b110100 !
b110100 $
0%
0#
#108
1#
#109
1&
b110101 !
b110101 $
1%
0#
#110
1#
#111
1(
1'
0&
b110110 !
b110110 $
0%
0#
#112
1#
#113
1&
b110111 !
b110111 $
1%
0#
#114
1#
#115
1,
1+
0*
0)
0(
0'
0&
b111000 !
b111000 $
0%
0#
#116
1#
#117
1&
b111001 !
b111001 $
1%
0#
#118
1#
#119
1(
1'
0&
b111010 !
b111010 $
0%
0#
#120
1#
#121
1&
b111011 !
b111011 $
1%
0#
#122
1#
#123
1*
1)
0(
0'
0&
b111100 !
b111100 $
0%
0#
#124
1#
#125
1&
b111101 !
b111101 $
1%
0#
#126
1#
#127
1(
1'
0&
b111110 !
b111110 $
0%
0#
#128
1#
#129
1&
b111111 !
b111111 $
1%
0#
#130
1#
#131
0"
11
00
0/
0.
0-
0,
0+
0*
0)
0(
0'
0&
b1000000 !
b1000000 $
0%
0#
#132
1#
#133
1&
b1000001 !
b1000001 $
1%
0#
#134
1#
#135
1(
1'
0&
b1000010 !
b1000010 $
0%
0#
#136
1#
#137
1&
b1000011 !
b1000011 $
1%
0#
#138
1#
#139
1*
1)
0(
0'
0&
b1000100 !
b1000100 $
0%
0#
#140
1#
#141
1&
b1000101 !
b1000101 $
1%
0#
#142
1#
#143
1(
1'
0&
b1000110 !
b1000110 $
0%
0#
#144
1#
#145
1&
b1000111 !
b1000111 $
1%
0#
#146
1#
#147
1,
1+
0*
0)
0(
0'
0&
b1001000 !
b1001000 $
0%
0#
#148
1#
#149
1&
b1001001 !
b1001001 $
1%
0#
#150
1#
#151
1(
1'
0&
b1001010 !
b1001010 $
0%
0#
#152
1#
#153
1&
b1001011 !
b1001011 $
1%
0#
#154
1#
#155
1*
1)
0(
0'
0&
b1001100 !
b1001100 $
0%
0#
#156
1#
#157
1&
b1001101 !
b1001101 $
1%
0#
#158
1#
#159
1(
1'
0&
b1001110 !
b1001110 $
0%
0#
#160
1#
#161
1&
b1001111 !
b1001111 $
1%
0#
#162
1#
#163
1.
1-
0,
0+
0*
0)
0(
0'
0&
b1010000 !
b1010000 $
0%
0#
#164
1#
#165
1&
b1010001 !
b1010001 $
1%
0#
#166
1#
#167
1(
1'
0&
b1010010 !
b1010010 $
0%
0#
#168
1#
#169
1&
b1010011 !
b1010011 $
1%
0#
#170
1#
#171
1*
1)
0(
0'
0&
b1010100 !
b1010100 $
0%
0#
#172
1#
#173
1&
b1010101 !
b1010101 $
1%
0#
#174
1#
#175
1(
1'
0&
b1010110 !
b1010110 $
0%
0#
#176
1#
#177
1&
b1010111 !
b1010111 $
1%
0#
#178
1#
#179
1,
1+
0*
0)
0(
0'
0&
b1011000 !
b1011000 $
0%
0#
#180
1#
#181
1&
b1011001 !
b1011001 $
1%
0#
#182
1#
#183
1(
1'
0&
b1011010 !
b1011010 $
0%
0#
#184
1#
#185
1&
b1011011 !
b1011011 $
1%
0#
#186
1#
#187
1*
1)
0(
0'
0&
b1011100 !
b1011100 $
0%
0#
#188
1#
#189
1&
b1011101 !
b1011101 $
1%
0#
#190
1#
#191
1(
1'
0&
b1011110 !
b1011110 $
0%
0#
#192
1#
#193
1&
b1011111 !
b1011111 $
1%
0#
#194
1#
#195
10
1/
0.
0-
0,
0+
0*
0)
0(
0'
0&
b1100000 !
b1100000 $
0%
0#
#196
1#
#197
1&
b1100001 !
b1100001 $
1%
0#
#198
1#
#199
1(
1'
0&
b1100010 !
b1100010 $
0%
0#
#200
1#
#201
1&
b1100011 !
b1100011 $
1%
0#
#202
1#
#203
1*
1)
0(
0'
0&
b1100100 !
b1100100 $
0%
0#
#204
1#
#205
1&
b1100101 !
b1100101 $
1%
0#
#206
1#
#207
1(
1'
0&
b1100110 !
b1100110 $
0%
0#
#208
1#
#209
1&
b1100111 !
b1100111 $
1%
0#
#210
1#
#211
1,
1+
0*
0)
0(
0'
0&
b1101000 !
b1101000 $
0%
0#
#212
1#
#213
1&
b1101001 !
b1101001 $
1%
0#
#214
1#
#215
1(
1'
0&
b1101010 !
b1101010 $
0%
0#
#216
1#
#217
1&
b1101011 !
b1101011 $
1%
0#
#218
1#
#219
1*
1)
0(
0'
0&
b1101100 !
b1101100 $
0%
0#
#220
1#
#221
1&
b1101101 !
b1101101 $
1%
0#
#222
1#
#223
1(
1'
0&
b1101110 !
b1101110 $
0%
0#
#224
1#
#225
1&
b1101111 !
b1101111 $
1%
0#
#226
1#
#227
1.
1-
0,
0+
0*
0)
0(
0'
0&
b1110000 !
b1110000 $
0%
0#
#228
1#
#229
1&
b1110001 !
b1110001 $
1%
0#
#230
1#
#231
1(
1'
0&
b1110010 !
b1110010 $
0%
0#
#232
1#
#233
1&
b1110011 !
b1110011 $
1%
0#
#234
1#
#235
1*
1)
0(
0'
0&
b1110100 !
b1110100 $
0%
0#
#236
1#
#237
1&
b1110101 !
b1110101 $
1%
0#
#238
1#
#239
1(
1'
0&
b1110110 !
b1110110 $
0%
0#
#240
1#
#241
1&
b1110111 !
b1110111 $
1%
0#
#242
1#
#243
1,
1+
0*
0)
0(
0'
0&
b1111000 !
b1111000 $
0%
0#
#244
1#
#245
1&
b1111001 !
b1111001 $
1%
0#
#246
1#
#247
1(
1'
0&
b1111010 !
b1111010 $
0%
0#
#248
1#
#249
1&
b1111011 !
b1111011 $
1%
0#
#250
1#
#251
1*
1)
0(
0'
0&
b1111100 !
b1111100 $
0%
0#
#252
1#
#253
1&
b1111101 !
b1111101 $
1%
0#
#254
1#
#255
1(
1'
0&
b1111110 !
b1111110 $
0%
0#
