mainproject/stationSystem/WasherPWM/WasherPWM.v
/*-------------------------------------------------------------
    Project Lab 1 - Main Project
       Program by: Zachary Bonneau
    Creation Date: 11/1/2023
     Program Name: WasherPWM
    SubProgram of: Station System
  
    Program Description:
        Drives PWM signals for electromagnet and servo motor

    Inputs:
        MCLK - timing clock
        controlServo - drives servo motor
    
    Outputs:  
        powerServo  - powers servo motor

*///-----------------------------------------------------------

// module code here
module WasherPWM(
    input CLK, controlServo,
    output powerServo);

    reg  [9:0] CCRServo = 0;
    wire [9:0] TCR;
    wire E;

    localparam [9:0] ServoUP   = 75,  // 0 deg
                     ServoDOWN = 68;  // -15 deg 


    always @(posedge E) begin
        case (controlServo)
            0: CCRServo = ServoUP;
            1: CCRServo = ServoDOWN;
        endcase
    end

    WasherTC TCR0(CLK, TCR, E);
    WasherOut ServoMotorOUT   (CLK, E, TCR, CCRServo, powerServo);

endmodule

module WasherTC(
    input CLK,
    output reg [9:0] TCR = -1,
    output reg E = 0
 );
    always@(negedge CLK) begin
        TCR <= TCR+1;
        case (TCR)
            0: E <= 1;
            975: TCR <= 0;
            default: E <= 0; // all other cases, E = 0
        endcase
    end
endmodule

module WasherOut(
    input CLK,
    input E,
    input [9:0] TCR, CCR,
    output reg out = 0
 );
    reg R = 0;

    always@(posedge CLK) begin
        case (TCR - CCR)
            0: R <= 1;
            default: R <= 0;
        endcase
    end

    always@(negedge CLK) begin
        out <= ~R & (out | E);
    end

endmodule

mainproject/stationSystem/WasherPWM/WasherPWMTST.v
/*-------------------------------------------------------------
    Project Lab 1 - Main Project
       Program by: Zachary Bonneau
    Creation Date: 
     Program Name: 
    SubProgram of: 
  
    Program Description:
*///-----------------------------------------------------------

// directive calls
`include "mainproject\\stationSystem\\WasherPWM\\WasherPWM.v"
`timescale 10us/10us


// module code here
module WasherTST();
    reg MCLK = 0;
    reg controlServo = 0;
    wire powerEM, powerServo;

    parameter PRD = 2;

    always#(PRD/2) begin
        MCLK = ~MCLK;
    end

    WasherPWM UUT(MCLK, controlServo, powerServo);

    initial begin
        $dumpfile("Washer.vcd");
        $dumpvars(0, WasherTST);
        #(PRD*900); 
        controlServo = 1;
        #(PRD*900);
        $finish;
    end

endmodule

build/Washer.vcd
$date
	Sun Nov 26 13:13:27 2023
$end
$version
	Icarus Verilog
$end
$timescale
	10us
$end
$scope module WasherTST $end
$var wire 1 ! powerServo $end
$var parameter 32 " PRD $end
$var reg 1 # MCLK $end
$var reg 1 $ controlServo $end
$scope module UUT $end
$var wire 1 # CLK $end
$var wire 1 $ controlServo $end
$var wire 1 ! powerServo $end
$var wire 10 % TCR [9:0] $end
$var wire 1 & E $end
$var parameter 10 ' ServoDOWN $end
$var parameter 10 ( ServoUP $end
$var reg 10 ) CCRServo [9:0] $end
$scope module ServoMotorOUT $end
$var wire 10 * CCR [9:0] $end
$var wire 1 # CLK $end
$var wire 10 + TCR [9:0] $end
$var wire 1 & E $end
$var reg 1 , R $end
$var reg 1 ! out $end
$upscope $end
$scope module TCR0 $end
$var wire 1 # CLK $end
$var reg 1 & E $end
$var reg 10 - TCR [9:0] $end
$upscope $end
$upscope $end
$upscope $end
$enddefinitions $end
$comment Show the parameter values. $end
$dumpall
b1001011 (
b1000100 '
b10 "
$end
#0
$dumpvars
b0 -
0,
b0 +
b0 *
b0 )
0&
b0 %
0$
0#
0!
$end
#1
1,
1#
#2
b1001011 )
b1001011 *
1&
b1 %
b1 +
b1 -
0#
#3
0,
1#
#4
0&
b10 %
b10 +
b10 -
1!
0#
#5
1#
#6
b11 %
b11 +
b11 -
0#
#7
1#
#8
b100 %
b100 +
b100 -
0#
#9
1#
#10
b101 %
b101 +
b101 -
0#
#11
1#
#12
b110 %
b110 +
b110 -
0#
#13
1#
#14
b111 %
b111 +
b111 -
0#
#15
1#
#16
b1000 %
b1000 +
b1000 -
0#
#17
1#
#18
b1001 %
b1001 +
b1001 -
0#
#19
1#
#20
b1010 %
b1010 +
b1010 -
0#
#21
1#
#22
b1011 %
b1011 +
b1011 -
0#
#23
1#
#24
b1100 %
b1100 +
b1100 -
0#
#25
1#
#26
b1101 %
b1101 +
b1101 -
0#
#27
1#
#28
b1110 %
b1110 +
b1110 -
0#
#29
1#
#30
b1111 %
b1111 +
b1111 -
0#
#31
1#
#32
b10000 %
b10000 +
b10000 -
0#
#33
1#
#34
b10001 %
b10001 +
b10001 -
0#
#35
1#
#36
b10010 %
b10010 +
b10010 -
0#
#37
1#
#38
b10011 %
b10011 +
b10011 -
0#
#39
1#
#40
b10100 %
b10100 +
b10100 -
0#
#41
1#
#42
b10101 %
b10101 +
b10101 -
0#
#43
1#
#44
b10110 %
b10110 +
b10110 -
0#
#45
1#
#46
b10111 %
b10111 +
b10111 -
0#
#47
1#
#48
b11000 %
b11000 +
b11000 -
0#
#49
1#
#50
b11001 %
b11001 +
b11001 -
0#
#51
1#
#52
b11010 %
b11010 +
b11010 -
0#
#53
1#
#54
b11011 %
b11011 +
b11011 -
0#
#55
1#
#56
b11100 %
b11100 +
b11100 -
0#
#57
1#
#58
b11101 %
b11101 +
b11101 -
0#
#59
1#
#60
b11110 %
b11110 +
b11110 -
0#
#61
1#
#62
b11111 %
b11111 +
b11111 -
0#
#63
1#
#64
b100000 %
b100000 +
b100000 -
0#
#65
1#
#66
b100001 %
b100001 +
b100001 -
0#
#67
1#
#68
b100010 %
b100010 +
b100010 -
0#
#69
1#
#70
b100011 %
b100011 +
b100011 -
0#
#71
1#
#72
b100100 %
b100100 +
b100100 -
0#
#73
1#
#74
b100101 %
b100101 +
b100101 -
0#
#75
1#
#76
b100110 %
b100110 +
b100110 -
0#
#77
1#
#78
b100111 %
b100111 +
b100111 -
0#
#79
1#
#80
b101000 %
b101000 +
b101000 -
0#
#81
1#
#82
b101001 %
b101001 +
b101001 -
0#
#83
1#
#84
b101010 %
b101010 +
b101010 -
0#
#85
1#
#86
b101011 %
b101011 +
b101011 -
0#
#87
1#
#88
b101100 %
b101100 +
b101100 -
0#
#89
1#
#90
b101101 %
b101101 +
b101101 -
0#
#91
1#
#92
b101110 %
b101110 +
b101110 -
0#
#93
1#
#94
b101111 %
b101111 +
b101111 -
0#
#95
1#
#96
b110000 %
b110000 +
b110000 -
0#
#97
1#
#98
b110001 %
b110001 +
b110001 -
0#
#99
1#
#100
b110010 %
b110010 +
b110010 -
0#
#101
1#
#102
b110011 %
b110011 +
b110011 -
0#
#103
1#
#104
b110100 %
b110100 +
b110100 -
0#
#105
1#
#106
b110101 %
b110101 +
b110101 -
0#
#107
1#
#108
b110110 %
b110110 +
b110110 -
0#
#109
1#
#110
b110111 %
b110111 +
b110111 -
0#
#111
1#
#112
b111000 %
b111000 +
b111000 -
0#
#113
1#
#114
b111001 %
b111001 +
b111001 -
0#
#115
1#
#116
b111010 %
b111010 +
b111010 -
0#
#117
1#
#118
b111011 %
b111011 +
b111011 -
0#
#119
1#
#120
b111100 %
b111100 +
b111100 -
0#
#121
1#
#122
b111101 %
b111101 +
b111101 -
0#
#123
1#
#124
b111110 %
b111110 +
b111110 -
0#
#125
1#
#126
b111111 %
b111111 +
b111111 -
0#
#127
1#
#128
b1000000 %
b1000000 +
b1000000 -
0#
#129
1#
#130
b1000001 %
b1000001 +
b1000001 -
0#
#131
1#
#132
b1000010 %
b1000010 +
b1000010 -
0#
#133
1#
#134
b1000011 %
b1000011 +
b1000011 -
0#
#135
1#
#136
b1000100 %
b1000100 +
b1000100 -
0#
#137
1#
#138
b1000101 %
b1000101 +
b1000101 -
0#
#139
1#
#140
b1000110 %
b1000110 +
b1000110 -
0#
#141
1#
#142
b1000111 %
b1000111 +
b1000111 -
0#
#143
1#
#144
b1001000 %
b1001000 +
b1001000 -
0#
#145
1#
#146
b1001001 %
b1001001 +
b1001001 -
0#
#147
1#
#148
b1001010 %
b1001010 +
b1001010 -
0#
#149
1#
#150
b1001011 %
b1001011 +
b1001011 -
0#
#151
1,
1#
#152
b1001100 %
b1001100 +
b1001100 -
0!
0#
#153
0,
1#
#154
b1001101 %
b1001101 +
b1001101 -
0#
#155
1#
#156
b1001110 %
b1001110 +
b1001110 -
0#
#157
1#
#158
b1001111 %
b1001111 +
b1001111 -
0#
#159
1#
#160
b1010000 %
b1010000 +
b1010000 -
0#
#161
1#
#162
b1010001 %
b1010001 +
b1010001 -
0#
#163
1#
#164
b1010010 %
b1010010 +
b1010010 -
0#
#165
1#
#166
b1010011 %
b1010011 +
b1010011 -
0#
#167
1#
#168
b1010100 %
b1010100 +
b1010100 -
0#
#169
1#
#170
b1010101 %
b1010101 +
b1010101 -
0#
#171
1#
#172
b1010110 %
b1010110 +
b1010110 -
0#
#173
1#
#174
b1010111 %
b1010111 +
b1010111 -
0#
#175
1#
#176
b1011000 %
b1011000 +
b1011000 -
0#
#177
1#
#178
b1011001 %
b1011001 +
b1011001 -
0#
#179
1#
#180
b1011010 %
b1011010 +
b1011010 -
0#
#181
1#
#182
b1011011 %
b1011011 +
b1011011 -
0#
#183
1#
#184
b1011100 %
b1011100 +
b1011100 -
0#
#185
1#
#186
b1011101 %
b1011101 +
b1011101 -
0#
#187
1#
#188
b1011110 %
b1011110 +
b1011110 -
0#
#189
1#
#190
b1011111 %
b1011111 +
b1011111 -
0#
#191
1#
#192
b1100000 %
b1100000 +
b1100000 -
0#
#193
1#
#194
b1100001 %
b1100001 +
b1100001 -
0#
#195
1#
#196
b1100010 %
b1100010 +
b1100010 -
0#
#197
1#
#198
b1100011 %
b1100011 +
b1100011 -
0#
#199
1#
#200
b1100100 %
b1100100 +
b1100100 -
0#
#201
1#
#202
b1100101 %
b1100101 +
b1100101 -
0#
#203
1#
#204
b1100110 %
b1100110 +
b1100110 -
0#
#205
1#
#206
b1100111 %
b1100111 +
b1100111 -
0#
#207
1#
#208
b1101000 %
b1101000 +
b1101000 -
0#
#209
1#
#210
b1101001 %
b1101001 +
b1101001 -
0#
#211
1#
#212
b1101010 %
b1101010 +
b1101010 -
0#
#213
1#
#214
b1101011 %
b1101011 +
b1101011 -
0#
#215
1#
#216
b1101100 %
b1101100 +
b1101100 -
0#
#217
1#
#218
b1101101 %
b1101101 +
b1101101 -
0#
#219
1#
#220
b1101110 %
b1101110 +
b1101110 -
0#
#221
1#
#222
b1101111 %
b1101111 +
b1101111 -
0#
#223
1#
#224
b1110000 %
b1110000 +
b1110000 -
0#
#225
1#
#226
b1110001 %
b1110001 +
b1110001 -
0#
#227
1#
#228
b1110010 %
b1110010 +
b1110010 -
0#
#229
1#
#230
b1110011 %
b1110011 +
b1110011 -
0#
#231
1#
#232
b1110100 %
b1110100 +
b1110100 -
0#
#233
1#
#234
b1110101 %
b1110101 +
b1110101 -
0#
#235
1#
#236
b1110110 %
b1110110 +
b1110110 -
0#
#237
1#
#238
b1110111 %
b1110111 +
b1110111 -
0#
#239
1#
#240
b1111000 %
b1111000 +
b1111000 -
0#
#241
1#
#242
b1111001 %
b1111001 +
b1111001 -
0#
#243
1#
#244
b1111010 %
b1111010 +
b1111010 -
0#
#245
1#
#246
b1111011 %
b1111011 +
b1111011 -
0#
#247
1#
#248
b1111100 %
b1111100 +
b1111100 -
0#
#249
1#
#250
b1111101 %
b1111101 +
b1111101 -
0#
#251
1#
#252
b1111110 %
b1111110 +
b1111110 -
0#
#253
1#
#254
b1111111 %
b1111111 +
b1111111 -
0#
#255
1#
#256
b10000000 %
b10000000 +
b10000000 -
0#
#257
1#
#258
b10000001 %
b10000001 +
b10000001 -
0#
#259
1#
#260
b10000010 %
b10000010 +
b10000010 -
0#
#261
1#
#262
b10000011 %
b10000011 +
b10000011 -
0#
#263
1#
#264
b10000100 %
b10000100 +
b10000100 -
0#
#265
1#
#266
b10000101 %
b10000101 +
b10000101 -
0#
#267
1#
#268
b10000110 %
b10000110 +
b10000110 -
0#
#269
1#
#270
b10000111 %
b10000111 +
b10000111 -
0#
#271
1#
#272
b10001000 %
b10001000 +
b10001000 -
0#
#273
1#
#274
b10001001 %
b10001001 +
b10001001 -
0#
#275
1#
#276
b10001010 %
b10001010 +
b10001010 -
0#
#277
1#
#278
b10001011 %
b10001011 +
b10001011 -
0#
#279
1#
#280
b10001100 %
b10001100 +
b10001100 -
0#
#281
1#
#282
b10001101 %
b10001101 +
b10001101 -
0#
#283
1#
#284
b10001110 %
b10001110 +
b10001110 -
0#
#285
1#
#286
b10001111 %
b10001111 +
b10001111 -
0#
#287
1#
#288
b10010000 %
b10010000 +
b10010000 -
0#
#289
1#
#290
b10010001 %
b10010001 +
b10010001 -
0#
#291
1#
#292
b10010010 %
b10010010 +
b10010010 -
0#
#293
1#
#294
b10010011 %
b10010011 +
b10010011 -
0#
#295
1#
#296
b10010100 %
b10010100 +
b10010100 -
0#
#297
1#
#298
b10010101 %
b10010101 +
b10010101 -
0#
#299
1#
#300
b10010110 %
b10010110 +
b10010110 -
0#
#301
1#
#302
b10010111 %
b10010111 +
b10010111 -
0#
#303
1#
#304
b10011000 %
b10011000 +
b10011000 -
0#
#305
1#
#306
b10011001 %
b10011001 +
b10011001 -
0#
#307
1#
#308
b10011010 %
b10011010 +
b10011010 -
0#
#309
1#
#310
b10011011 %
b10011011 +
b10011011 -
0#
#311
1#
#312
b10011100 %
b10011100 +
b10011100 -
0#
#313
1#
#314
b10011101 %
b10011101 +
b10011101 -
0#
#315
1#
#316
b10011110 %
b10011110 +
b10011110 -
0#
#317
1#
#318
b10011111 %
b10011111 +
b10011111 -
0#
#319
1#
#320
b10100000 %
b10100000 +
b10100000 -
0#
#321
1#
#322
b10100001 %
b10100001 +
b10100001 -
0#
#323
1#
#324
b10100010 %
b10100010 +
b10100010 -
0#
#325
1#
#326
b10100011 %
b10100011 +
b10100011 -
0#
#327
1#
#328
b10100100 %
b10100100 +
b10100100 -
0#
#329
1#
#330
b10100101 %
b10100101 +
b10100101 -
0#
#331
1#
#332
b10100110 %
b10100110 +
b10100110 -
0#
#333
1#
#334
b10100111 %
b10100111 +
b10100111 -
0#
#335
1#
#336
b10101000 %
b10101000 +
b10101000 -
0#
#337
1#
#338
b10101001 %
b10101001 +
b10101001 -
0#
#339
1#
#340
b10101010 %
b10101010 +
b10101010 -
0#
#341
1#
#342
b10101011 %
b10101011 +
b10101011 -
0#
#343
1#
#344
b10101100 %
b10101100 +
b10101100 -
0#
#345
1#
#346
b10101101 %
b10101101 +
b10101101 -
0#
#347
1#
#348
b10101110 %
b10101110 +
b10101110 -
0#
#349
1#
#350
b10101111 %
b10101111 +
b10101111 -
0#
#351
1#
#352
b10110000 %
b10110000 +
b10110000 -
0#
#353
1#
#354
b10110001 %
b10110001 +
b10110001 -
0#
#355
1#
#356
b10110010 %
b10110010 +
b10110010 -
0#
#357
1#
#358
b10110011 %
b10110011 +
b10110011 -
0#
#359
1#
#360
b10110100 %
b10110100 +
b10110100 -
0#
#361
1#
#362
b10110101 %
b10110101 +
b10110101 -
0#
#363
1#
#364
b10110110 %
b10110110 +
b10110110 -
0#
#365
1#
#366
b10110111 %
b10110111 +
b10110111 -
0#
#367
1#
#368
b10111000 %
b10111000 +
b10111000 -
0#
#369
1#
#370
b10111001 %
b10111001 +
b10111001 -
0#
#371
1#
#372
b10111010 %
b10111010 +
b10111010 -
0#
#373
1#
#374
b10111011 %
b10111011 +
b10111011 -
0#
#375
1#
#376
b10111100 %
b10111100 +
b10111100 -
0#
#377
1#
#378
b10111101 %
b10111101 +
b10111101 -
0#
#379
1#
#380
b10111110 %
b10111110 +
b10111110 -
0#
#381
1#
#382
b10111111 %
b10111111 +
b10111111 -
0#
#383
1#
#384
b11000000 %
b11000000 +
b11000000 -
0#
#385
1#
#386
b11000001 %
b11000001 +
b11000001 -
0#
#387
1#
#388
b11000010 %
b11000010 +
b11000010 -
0#
#389
1#
#390
b11000011 %
b11000011 +
b11000011 -
0#
#391
1#
#392
b11000100 %
b11000100 +
b11000100 -
0#
#393
1#
#394
b11000101 %
b11000101 +
b11000101 -
0#
#395
1#
#396
b11000110 %
b11000110 +
b11000110 -
0#
#397
1#
#398
b11000111 %
b11000111 +
b11000111 -
0#
#399
1#
#400
b11001000 %
b11001000 +
b11001000 -
0#
#401
1#
#402
b11001001 %
b11001001 +
b11001001 -
0#
#403
1#
#404
b11001010 %
b11001010 +
b11001010 -
0#
#405
1#
#406
b11001011 %
b11001011 +
b11001011 -
0#
#407
1#
#408
b11001100 %
b11001100 +
b11001100 -
0#
#409
1#
#410
b11001101 %
b11001101 +
b11001101 -
0#
#411
1#
#412
b11001110 %
b11001110 +
b11001110 -
0#
#413
1#
#414
b11001111 %
b11001111 +
b11001111 -
0#
#415
1#
#416
b11010000 %
b11010000 +
b11010000 -
0#
#417
1#
#418
b11010001 %
b11010001 +
b11010001 -
0#
#419
1#
#420
b11010010 %
b11010010 +
b11010010 -
0#
#421
1#
#422
b11010011 %
b11010011 +
b11010011 -
0#
#423
1#
#424
b11010100 %
b11010100 +
b11010100 -
0#
#425
1#
#426
b11010101 %
b11010101 +
b11010101 -
0#
#427
1#
#428
b11010110 %
b11010110 +
b11010110 -
0#
#429
1#
#430
b11010111 %
b11010111 +
b11010111 -
0#
#431
1#
#432
b11011000 %
b11011000 +
b11011000 -
0#
#433
1#
#434
b11011001 %
b11011001 +
b11011001 -
0#
#435
1#
#436
b11011010 %
b11011010 +
b11011010 -
0#
#437
1#
#438
b11011011 %
b11011011 +
b11011011 -
0#
#439
1#
#440
b11011100 %
b11011100 +
b11011100 -
0#
#441
1#
#442
b11011101 %
b11011101 +
b11011101 -
0#
#443
1#
#444
b11011110 %
b11011110 +
b11011110 -
0#
#445
1#
#446
b11011111 %
b11011111 +
b11011111 -
0#
#447
1#
#448
b11100000 %
b11100000 +
b11100000 -
0#
#449
1#
#450
b11100001 %
b11100001 +
b11100001 -
0#
#451
1#
#452
b11100010 %
b11100010 +
b11100010 -
0#
#453
1#
#454
b11100011 %
b11100011 +
b11100011 -
0#
#455
1#
#456
b11100100 %
b11100100 +
b11100100 -
0#
#457
1#
#458
b11100101 %
b11100101 +
b11100101 -
0#
#459
1#
#460
b11100110 %
b11100110 +
b11100110 -
0#
#461
1#
#462
b11100111 %
b11100111 +
b11100111 -
0#
#463
1#
#464
b11101000 %
b11101000 +
b11101000 -
0#
#465
1#
#466
b11101001 %
b11101001 +
b11101001 -
0#
#467
1#
#468
b11101010 %
b11101010 +
b11101010 -
0#
#469
1#
#470
b11101011 %
b11101011 +
b11101011 -
0#
#471
1#
#472
b11101100 %
b11101100 +
b11101100 -
0#
#473
1#
#474
b11101101 %
b11101101 +
b11101101 -
0#
#475
1#
#476
b11101110 %
b11101110 +
b11101110 -
0#
#477
1#
#478
b11101111 %
b11101111 +
b11101111 -
0#
#479
1#
#480
b11110000 %
b11110000 +
b11110000 -
0#
#481
1#
#482
b11110001 %
b11110001 +
b11110001 -
0#
#483
1#
#484
b11110010 %
b11110010 +
b11110010 -
0#
#485
1#
#486
b11110011 %
b11110011 +
b11110011 -
0#
#487
1#
#488
b11110100 %
b11110100 +
b11110100 -
0#
#489
1#
#490
b11110101 %
b11110101 +
b11110101 -
0#
#491
1#
#492
b11110110 %
b11110110 +
b11110110 -
0#
#493
1#
#494
b11110111 %
b11110111 +
b11110111 -
0#
#495
1#
#496
b11111000 %
b11111000 +
b11111000 -
0#
#497
1#
#498
b11111001 %
b11111001 +
b11111001 -
0#
#499
1#
#500
b11111010 %
b11111010 +
b11111010 -
0#
#501
1#
#502
b11111011 %
b11111011 +
b11111011 -
0#
#503
1#
#504
b11111100 %
b11111100 +
b11111100 -
0#
#505
1#
#506
b11111101 %
b11111101 +
b11111101 -
0#
#507
1#
#508
b11111110 %
b11111110 +
b11111110 -
0#
#509
1#
#510
b11111111 %
b11111111 +
b11111111 -
0#
#511
1#
#512
b100000000 %
b100000000 +
b100000000 -
0#
#513
1#
#514
b100000001 %
b100000001 +
b100000001 -
0#
#515
1#
#516
b100000010 %
b100000010 +
b100000010 -
0#
#517
1#
#518
b100000011 %
b100000011 +
b100000011 -
0#
#519
1#
#520
b100000100 %
b100000100 +
b100000100 -
0#
#521
1#
#522
b100000101 %
b100000101 +
b100000101 -
0#
#523
1#
#524
b100000110 %
b100000110 +
b100000110 -
0#
#525
1#
#526
b100000111 %
b100000111 +
b100000111 -
0#
#527
1#
#528
b100001000 %
b100001000 +
b100001000 -
0#
#529
1#
#530
b100001001 %
b100001001 +
b100001001 -
0#
#531
1#
#532
b100001010 %
b100001010 +
b100001010 -
0#
#533
1#
#534
b100001011 %
b100001011 +
b100001011 -
0#
#535
1#
#536
b100001100 %
b100001100 +
b100001100 -
0#
#537
1#
#538
b100001101 %
b100001101 +
b100001101 -
0#
#539
1#
#540
b100001110 %
b100001110 +
b100001110 -
0#
#541
1#
#542
b100001111 %
b100001111 +
b100001111 -
0#
#543
1#
#544
b100010000 %
b100010000 +
b100010000 -
0#
#545
1#
#546
b100010001 %
b100010001 +
b100010001 -
0#
#547
1#
#548
b100010010 %
b100010010 +
b100010010 -
0#
#549
1#
#550
b100010011 %
b100010011 +
b100010011 -
0#
#551
1#
#552
b100010100 %
b100010100 +
b100010100 -
0#
#553
1#
#554
b100010101 %
b100010101 +
b100010101 -
0#
#555
1#
#556
b100010110 %
b100010110 +
b100010110 -
0#
#557
1#
#558
b100010111 %
b100010111 +
b100010111 -
0#
#559
1#
#560
b100011000 %
b100011000 +
b100011000 -
0#
#561
1#
#562
b100011001 %
b100011001 +
b100011001 -
0#
#563
1#
#564
b100011010 %
b100011010 +
b100011010 -
0#
#565
1#
#566
b100011011 %
b100011011 +
b100011011 -
0#
#567
1#
#568
b100011100 %
b100011100 +
b100011100 -
0#
#569
1#
#570
b100011101 %
b100011101 +
b100011101 -
0#
#571
1#
#572
b100011110 %
b100011110 +
b100011110 -
0#
#573
1#
#574
b100011111 %
b100011111 +
b100011111 -
0#
#575
1#
#576
b100100000 %
b100100000 +
b100100000 -
0#
#577
1#
#578
b100100001 %
b100100001 +
b100100001 -
0#
#579
1#
#580
b100100010 %
b100100010 +
b100100010 -
0#
#581
1#
#582
b100100011 %
b100100011 +
b100100011 -
0#
#583
1#
#584
b100100100 %
b100100100 +
b100100100 -
0#
#585
1#
#586
b100100101 %
b100100101 +
b100100101 -
0#
#587
1#
#588
b100100110 %
b100100110 +
b100100110 -
0#
#589
1#
#590
b100100111 %
b100100111 +
b100100111 -
0#
#591
1#
#592
b100101000 %
b100101000 +
b100101000 -
0#
#593
1#
#594
b100101001 %
b100101001 +
b100101001 -
0#
#595
1#
#596
b100101010 %
b100101010 +
b100101010 -
0#
#597
1#
#598
b100101011 %
b100101011 +
b100101011 -
0#
#599
1#
#600
b100101100 %
b100101100 +
b100101100 -
0#
#601
1#
#602
b100101101 %
b100101101 +
b100101101 -
0#
#603
1#
#604
b100101110 %
b100101110 +
b100101110 -
0#
#605
1#
#606
b100101111 %
b100101111 +
b100101111 -
0#
#607
1#
#608
b100110000 %
b100110000 +
b100110000 -
0#
#609
1#
#610
b100110001 %
b100110001 +
b100110001 -
0#
#611
1#
#612
b100110010 %
b100110010 +
b100110010 -
0#
#613
1#
#614
b100110011 %
b100110011 +
b100110011 -
0#
#615
1#
#616
b100110100 %
b100110100 +
b100110100 -
0#
#617
1#
#618
b100110101 %
b100110101 +
b100110101 -
0#
#619
1#
#620
b100110110 %
b100110110 +
b100110110 -
0#
#621
1#
#622
b100110111 %
b100110111 +
b100110111 -
0#
#623
1#
#624
b100111000 %
b100111000 +
b100111000 -
0#
#625
1#
#626
b100111001 %
b100111001 +
b100111001 -
0#
#627
1#
#628
b100111010 %
b100111010 +
b100111010 -
0#
#629
1#
#630
b100111011 %
b100111011 +
b100111011 -
0#
#631
1#
#632
b100111100 %
b100111100 +
b100111100 -
0#
#633
1#
#634
b100111101 %
b100111101 +
b100111101 -
0#
#635
1#
#636
b100111110 %
b100111110 +
b100111110 -
0#
#637
1#
#638
b100111111 %
b100111111 +
b100111111 -
0#
#639
1#
#640
b101000000 %
b101000000 +
b101000000 -
0#
#641
1#
#642
b101000001 %
b101000001 +
b101000001 -
0#
#643
1#
#644
b101000010 %
b101000010 +
b101000010 -
0#
#645
1#
#646
b101000011 %
b101000011 +
b101000011 -
0#
#647
1#
#648
b101000100 %
b101000100 +
b101000100 -
0#
#649
1#
#650
b101000101 %
b101000101 +
b101000101 -
0#
#651
1#
#652
b101000110 %
b101000110 +
b101000110 -
0#
#653
1#
#654
b101000111 %
b101000111 +
b101000111 -
0#
#655
1#
#656
b101001000 %
b101001000 +
b101001000 -
0#
#657
1#
#658
b101001001 %
b101001001 +
b101001001 -
0#
#659
1#
#660
b101001010 %
b101001010 +
b101001010 -
0#
#661
1#
#662
b101001011 %
b101001011 +
b101001011 -
0#
#663
1#
#664
b101001100 %
b101001100 +
b101001100 -
0#
#665
1#
#666
b101001101 %
b101001101 +
b101001101 -
0#
#667
1#
#668
b101001110 %
b101001110 +
b101001110 -
0#
#669
1#
#670
b101001111 %
b101001111 +
b101001111 -
0#
#671
1#
#672
b101010000 %
b101010000 +
b101010000 -
0#
#673
1#
#674
b101010001 %
b101010001 +
b101010001 -
0#
#675
1#
#676
b101010010 %
b101010010 +
b101010010 -
0#
#677
1#
#678
b101010011 %
b101010011 +
b101010011 -
0#
#679
1#
#680
b101010100 %
b101010100 +
b101010100 -
0#
#681
1#
#682
b101010101 %
b101010101 +
b101010101 -
0#
#683
1#
#684
b101010110 %
b101010110 +
b101010110 -
0#
#685
1#
#686
b101010111 %
b101010111 +
b101010111 -
0#
#687
1#
#688
b101011000 %
b101011000 +
b101011000 -
0#
#689
1#
#690
b101011001 %
b101011001 +
b101011001 -
0#
#691
1#
#692
b101011010 %
b101011010 +
b101011010 -
0#
#693
1#
#694
b101011011 %
b101011011 +
b101011011 -
0#
#695
1#
#696
b101011100 %
b101011100 +
b101011100 -
0#
#697
1#
#698
b101011101 %
b101011101 +
b101011101 -
0#
#699
1#
#700
b101011110 %
b101011110 +
b101011110 -
0#
#701
1#
#702
b101011111 %
b101011111 +
b101011111 -
0#
#703
1#
#704
b101100000 %
b101100000 +
b101100000 -
0#
#705
1#
#706
b101100001 %
b101100001 +
b101100001 -
0#
#707
1#
#708
b101100010 %
b101100010 +
b101100010 -
0#
#709
1#
#710
b101100011 %
b101100011 +
b101100011 -
0#
#711
1#
#712
b101100100 %
b101100100 +
b101100100 -
0#
#713
1#
#714
b101100101 %
b101100101 +
b101100101 -
0#
#715
1#
#716
b101100110 %
b101100110 +
b101100110 -
0#
#717
1#
#718
b101100111 %
b101100111 +
b101100111 -
0#
#719
1#
#720
b101101000 %
b101101000 +
b101101000 -
0#
#721
1#
#722
b101101001 %
b101101001 +
b101101001 -
0#
#723
1#
#724
b101101010 %
b101101010 +
b101101010 -
0#
#725
1#
#726
b101101011 %
b101101011 +
b101101011 -
0#
#727
1#
#728
b101101100 %
b101101100 +
b101101100 -
0#
#729
1#
#730
b101101101 %
b101101101 +
b101101101 -
0#
#731
1#
#732
b101101110 %
b101101110 +
b101101110 -
0#
#733
1#
#734
b101101111 %
b101101111 +
b101101111 -
0#
#735
1#
#736
b101110000 %
b101110000 +
b101110000 -
0#
#737
1#
#738
b101110001 %
b101110001 +
b101110001 -
0#
#739
1#
#740
b101110010 %
b101110010 +
b101110010 -
0#
#741
1#
#742
b101110011 %
b101110011 +
b101110011 -
0#
#743
1#
#744
b101110100 %
b101110100 +
b101110100 -
0#
#745
1#
#746
b101110101 %
b101110101 +
b101110101 -
0#
#747
1#
#748
b101110110 %
b101110110 +
b101110110 -
0#
#749
1#
#750
b101110111 %
b101110111 +
b101110111 -
0#
#751
1#
#752
b101111000 %
b101111000 +
b101111000 -
0#
#753
1#
#754
b101111001 %
b101111001 +
b101111001 -
0#
#755
1#
#756
b101111010 %
b101111010 +
b101111010 -
0#
#757
1#
#758
b101111011 %
b101111011 +
b101111011 -
0#
#759
1#
#760
b101111100 %
b101111100 +
b101111100 -
0#
#761
1#
#762
b101111101 %
b101111101 +
b101111101 -
0#
#763
1#
#764
b101111110 %
b101111110 +
b101111110 -
0#
#765
1#
#766
b101111111 %
b101111111 +
b101111111 -
0#
#767
1#
#768
b110000000 %
b110000000 +
b110000000 -
0#
#769
1#
#770
b110000001 %
b110000001 +
b110000001 -
0#
#771
1#
#772
b110000010 %
b110000010 +
b110000010 -
0#
#773
1#
#774
b110000011 %
b110000011 +
b110000011 -
0#
#775
1#
#776
b110000100 %
b110000100 +
b110000100 -
0#
#777
1#
#778
b110000101 %
b110000101 +
b110000101 -
0#
#779
1#
#780
b110000110 %
b110000110 +
b110000110 -
0#
#781
1#
#782
b110000111 %
b110000111 +
b110000111 -
0#
#783
1#
#784
b110001000 %
b110001000 +
b110001000 -
0#
#785
1#
#786
b110001001 %
b110001001 +
b110001001 -
0#
#787
1#
#788
b110001010 %
b110001010 +
b110001010 -
0#
#789
1#
#790
b110001011 %
b110001011 +
b110001011 -
0#
#791
1#
#792
b110001100 %
b110001100 +
b110001100 -
0#
#793
1#
#794
b110001101 %
b110001101 +
b110001101 -
0#
#795
1#
#796
b110001110 %
b110001110 +
b110001110 -
0#
#797
1#
#798
b110001111 %
b110001111 +
b110001111 -
0#
#799
1#
#800
b110010000 %
b110010000 +
b110010000 -
0#
#801
1#
#802
b110010001 %
b110010001 +
b110010001 -
0#
#803
1#
#804
b110010010 %
b110010010 +
b110010010 -
0#
#805
1#
#806
b110010011 %
b110010011 +
b110010011 -
0#
#807
1#
#808
b110010100 %
b110010100 +
b110010100 -
0#
#809
1#
#810
b110010101 %
b110010101 +
b110010101 -
0#
#811
1#
#812
b110010110 %
b110010110 +
b110010110 -
0#
#813
1#
#814
b110010111 %
b110010111 +
b110010111 -
0#
#815
1#
#816
b110011000 %
b110011000 +
b110011000 -
0#
#817
1#
